zx0/__init__.py
zx0/compress.py
zx0/optimize.py
zx0/zx0.py
zx0/zx0_common.py
zx0-2.2.0.dist-info/licenses/LICENSE
zx0-2.2.0.dist-info/METADATA
zx0-2.2.0.dist-info/WHEEL
zx0-2.2.0.dist-info/entry_points.txt
zx0-2.2.0.dist-info/top_level.txt
zx0-2.2.0.dist-info/RECORD
